{"file-format": {"type": "diffrend", "version": "0.1"},
 "glsl": {"vertex": "./shaders/phong/vs.glsl", "fragment": "./shaders/phong/fs.glsl"},
 "camera": {
    "proj_type": "perspective",
    "viewport": [0, 0, 320, 240],
    "fovy": 1.572,
    "focal_length": 0.1,
    "eye": [0.0, 0.0, 1.0, 1.0],
    "up": [0.0, 1.0, 0.0, 0.0],
    "at": [0.0, 0.0, 0.0, 1.0],
    "near": 0.1, "far": 1000.0
    },
 "lights": {"pos": [[0.0, 0.0, 2.0, 1.0]
        ],
    "color_idx": [1],
    "attenuation": [[1.0, 0.0, 0.0]],
    "ambient": [0.0, 0.0, 0.0]
    },
 "colors": [[0.0, 0.0, 0.0], [0.8, 0.1, 0.1]],
 "materials": {
     "albedo": [[0.5, 0.5, 0.5]],
     "coeffs": [[1.0, 0.0, 0.0]]
  },
 "objects": {"obj": [{"path": "./objs/quad.obj", "material_idx": 0}]},
 "tonemap": {"type": "gamma", "gamma": [0.8]}
}
